netrunner/__init__.py
netrunner/connections/__init__.py
netrunner/connections/base.py
netrunner/connections/ssh.py
netrunner/host/__init__.py
netrunner/host/errors.py
netrunner/host/host.py
netrunner/runner/__init__.py
netrunner/runner/credentials.py
netrunner/runner/errors.py
netrunner/runner/response.py
netrunner/runner/runner.py
netrunner/task/__init__.py
netrunner/task/task.py
aionetrunner-0.1.0.dist-info/WHEEL
aionetrunner-0.1.0.dist-info/METADATA
aionetrunner-0.1.0.dist-info/RECORD
